{"filename": "errol_mclaughlin_jr__10001__DKR_400bp_11-19-01.xlsx_AIG Weather.csv", "header": ["Counterparty", "Deal Date", "Fin / Phy", "Period", "Notional", "Volume", "Fixed", "Mid", "MtM Value"], "content": [["AARB", "2001-10-29 00:00:00", "F", "2001-11-01 00:00:00", "460", "1", "650", "590", "-27600"], ["AIGCOMARB", "2001-10-29 00:00:00", "F", "2001-11-01 00:00:00", "1540", "1", "650", "590", "-92400"], ["AARB", "2001-10-29 00:00:00", "F", "2001-11-01 00:00:00", "460", "-1", "610", "590", "9200"], ["AIGCOMARB", "2001-10-29 00:00:00", "F", "2001-11-01 00:00:00", "1540", "-1", "610", "590", "30800"]], "target": "deex", "label": "3", "table_NE": [["PERSON", "PERSON", "PERSON", "PERSON"], ["DATE", "DATE", "DATE", "DATE"], [], ["DATE", "DATE", "DATE", "DATE"], [], [], [], [], []], "most_common": ["PERSON2", "DATE3", "EMPTY", "DATE3", "EMPTY", "EMPTY", "EMPTY", "EMPTY", "EMPTY"], "related_table": ["errol_mclaughlin_jr__10001__DKR_400bp_11-19-01.xlsx_AIG Weather.csv"]}