{"filename": "C10093_C10093.csv", "header": ["Industry", "Patents", "Enterprises"], "content": [["10-12\u00a0Food\u00a0industry", "6", "5"], ["13-15\u00a0Textile,\u00a0clothing,\u00a0leather\u00a0and\u00a0footwear\u00a0industry", "2", "2"], ["16-17\u00a0Wood\u00a0and\u00a0paper\u00a0industry", "14", "6"], ["19-22\u00a0Chemical\u00a0industry", "38", "15"], ["24-25,\u00a028-30\u00a0Metal\u00a0and\u00a0engineering\u00a0industry", "128", "41"], ["26-27\u00a0Electrical\u00a0and\u00a0electronics\u00a0industry", "432", "28"], ["Other\u00a0manufacturing", "25", "15"], ["D,E\u00a0Electricity,\u00a0gas\u00a0and\u00a0water\u00a0supply", "1", "1"], ["F\u00a0Construction", "2", "2"], ["G\u00a0Wholesale\u00a0and\u00a0retail\u00a0trade", "9", "7"], ["J\u00a0Information\u00a0and\u00a0communication", "32", "13"], ["72\u00a0Scientific\u00a0research\u00a0and\u00a0development", "22", "15"], ["M\u00a0Professional,\u00a0scientific\u00a0and\u00a0technical\u00a0activities\u00a0(excl.\u00a072)", "23", "15"], ["Other\u00a0industries", "38", "4"]], "target": "0", "label": "Industry", "table_NE": [["CARDINAL", "CARDINAL", "CARDINAL", "CARDINAL", "CARDINAL", "CARDINAL", "CARDINAL", "CARDINAL"], ["CARDINAL", "CARDINAL", "CARDINAL", "CARDINAL", "CARDINAL", "CARDINAL", "CARDINAL", "CARDINAL", "CARDINAL", "CARDINAL", "CARDINAL", "CARDINAL", "CARDINAL", "CARDINAL"], ["CARDINAL", "CARDINAL", "CARDINAL", "CARDINAL", "CARDINAL", "CARDINAL", "CARDINAL", "CARDINAL", "CARDINAL", "CARDINAL", "CARDINAL", "CARDINAL", "CARDINAL", "CARDINAL"]], "most_common": ["CARDINAL", "CARDINAL", "CARDINAL"], "related_table": ["C10093_C10093.csv"], "subtable": ["Arson_Table_1_Arson_Rate_by_Population_Group_2017.xls_17arsontbl1.csv", "Expanded_Homicide_Data_Table_4_Murder_by_Victim_Offender_Situations_2017.xls_17shrtbl04.csv", "07arsontbl1.xls_Sheet1.csv", "0b62ac60-cc3a-46c9-a261-e0059011ad68.xlsx_Charter Schools.csv", "0b62ac60-cc3a-46c9-a261-e0059011ad68.xlsx_School Districts.csv", "3aa2b81d-aa4f-44ba-af17-e28dcb76d616.xls_Insider Ownership.csv", "0be0ebf4-84ac-4e31-83ee-412e728c82fa.xls_Insider Ownership.csv", "6a193820-fef7-44ac-9d86-4fcbe38e65eb.xls_Insider Ownership.csv", "before-entry1-q3-2012-tabs.xls_cs.03.csv", "SC SF1 Air pollution.xlsx_SC SF1 Air Pollution.csv", "C10154_C10154.csv", "C10138_C10138.csv"], "subtable-type": ["AA", "XAA", "AA", "APAA", "APAA", "DAAA", "DAAA", "DAAA", "AXAA", "IAAA", "IAA", "BAA"], "table-type": "AAA"}