{"filename": "07tbl54.xls_TABLE42k.csv", "header": ["Offense charged", "Number of persons arrested Total", "Male", "Female", "Percent male", "Percent female", "Percent distribution1 Total", "Male", "Female", "", ""], "content": [["Murder and nonnegligent manslaughter", "1944.0", "1727.0", "217.0", "88.8", "11.2", "0.1", "0.1", "0.1", "", ""], ["Forcible rape", "3002.0", "2967.0", "35.0", "98.8", "1.2", "0.2", "0.2", "*", "", ""], ["Robbery", "11428.0", "10210.0", "1218.0", "89.3", "10.7", "0.6", "0.8", "0.3", "", ""], ["Aggravated assault", "56233.0", "45116.0", "11117.0", "80.2", "19.8", "3.2", "3.3", "2.7", "", ""], ["Burglary", "39235.0", "34075.0", "5160.0", "86.8", "13.2", "2.2", "2.5", "1.3", "", ""], ["Larceny-theft", "105297.0", "67300.0", "37997.0", "63.9", "36.1", "6.0", "4.9", "9.3", "", ""], ["Motor vehicle theft", "13938.0", "11475.0", "2463.0", "82.3", "17.7", "0.8", "0.8", "0.6", "", ""], ["Arson", "2153.0", "1808.0", "345.0", "84.0", "16.0", "0.1", "0.1", "0.1", "", ""], ["Violent crime2", "72607.0", "60020.0", "12587.0", "82.7", "17.3", "4.1", "4.4", "3.1", "", ""], ["Property crime2", "160623.0", "114658.0", "45965.0", "71.4", "28.6", "9.1", "8.4", "11.2", "", ""], ["Other assaults", "161719.0", "120932.0", "40787.0", "74.8", "25.2", "9.1", "8.9", "10.0", "", ""], ["Forgery and counterfeiting", "13104.0", "8152.0", "4952.0", "62.2", "37.8", "0.7", "0.6", "1.2", "", ""], ["Fraud", "51702.0", "27296.0", "24406.0", "52.8", "47.2", "2.9", "2.0", "6.0", "", ""], ["Embezzlement", "2635.0", "1295.0", "1340.0", "49.1", "50.9", "0.1", "0.1", "0.3", "", ""], ["Stolen property; buying, receiving, possessing", "15625.0", "12874.0", "2751.0", "82.4", "17.6", "0.9", "0.9", "0.7", "", ""], ["Vandalism", "30259.0", "25225.0", "5034.0", "83.4", "16.6", "1.7", "1.9", "1.2", "", ""], ["Weapons; carrying, possessing, etc.", "21066.0", "19351.0", "1715.0", "91.9", "8.1", "1.2", "1.4", "0.4", "", ""], ["Prostitution and commercialized vice", "2484.0", "980.0", "1504.0", "39.5", "60.5", "0.1", "0.1", "0.4", "", ""], ["Sex offenses (except forcible rape and prostitution)", "12065.0", "11354.0", "711.0", "94.1", "5.9", "0.7", "0.8", "0.2", "", ""], ["Drug abuse violations", "222026.0", "178181.0", "43845.0", "80.3", "19.7", "12.6", "13.1", "10.7", "", ""], ["Gambling", "601.0", "485.0", "116.0", "80.7", "19.3", "*", "*", "*", "", ""], ["Offenses against the family and children", "35576.0", "29677.0", "5899.0", "83.4", "16.6", "2.0", "2.2", "1.4", "", ""], ["Driving under the influence", "241360.0", "193832.0", "47528.0", "80.3", "19.7", "13.6", "14.3", "11.6", "", ""], ["Liquor laws", "55089.0", "39265.0", "15824.0", "71.3", "28.7", "3.1", "2.9", "3.9", "", ""], ["Drunkenness", "40058.0", "33042.0", "7016.0", "82.5", "17.5", "2.3", "2.4", "1.7", "", ""], ["Disorderly conduct", "49347.0", "36088.0", "13259.0", "73.1", "26.9", "2.8", "2.7", "3.2", "", ""], ["Vagrancy", "2482.0", "1816.0", "666.0", "73.2", "26.8", "0.1", "0.1", "0.2", "", ""], ["All other offenses (except traffic)", "558677.0", "435379.0", "123298.0", "77.9", "22.1", "31.6", "32.0", "30.1", "", ""], ["Suspicion", "617.0", "464.0", "153.0", "75.2", "24.8", "*", "*", "*", "", ""], ["Curfew and loitering law violations", "3873.0", "2547.0", "1326.0", "65.8", "34.2", "0.2", "0.2", "0.3", "", ""], ["Runaways", "15245.0", "6978.0", "8267.0", "45.8", "54.2", "0.9", "0.5", "2.0", "", ""]], "target": "0", "label": "CriminalCharge", "table_NE": [[], ["CARDINAL", "CARDINAL", "CARDINAL", "CARDINAL", "CARDINAL", "CARDINAL", "CARDINAL", "CARDINAL", "CARDINAL", "CARDINAL", "CARDINAL", "CARDINAL", "CARDINAL", "CARDINAL", "CARDINAL", "CARDINAL"], ["CARDINAL", "CARDINAL", "CARDINAL", "CARDINAL", "CARDINAL", "CARDINAL", "CARDINAL", "CARDINAL", "CARDINAL", "CARDINAL", "CARDINAL", "CARDINAL", "CARDINAL", "CARDINAL", "CARDINAL", "CARDINAL", "CARDINAL", "CARDINAL", "CARDINAL", "CARDINAL", "CARDINAL", "CARDINAL"], ["CARDINAL", "CARDINAL", "CARDINAL", "CARDINAL", "CARDINAL", "CARDINAL", "CARDINAL", "CARDINAL", "CARDINAL", "CARDINAL", "CARDINAL", "CARDINAL", "CARDINAL", "CARDINAL", "CARDINAL", "CARDINAL", "CARDINAL", "CARDINAL", "CARDINAL", "CARDINAL", "CARDINAL", "CARDINAL", "CARDINAL", "CARDINAL", "CARDINAL", "CARDINAL", "CARDINAL", "CARDINAL", "CARDINAL", "CARDINAL"], ["CARDINAL", "CARDINAL", "CARDINAL", "CARDINAL", "CARDINAL", "CARDINAL", "CARDINAL", "CARDINAL", "CARDINAL", "CARDINAL", "CARDINAL", "CARDINAL", "CARDINAL", "CARDINAL", "CARDINAL", "CARDINAL", "CARDINAL", "CARDINAL", "CARDINAL", "CARDINAL", "CARDINAL", "CARDINAL", "CARDINAL", "CARDINAL", "CARDINAL", "CARDINAL", "CARDINAL", "CARDINAL", "CARDINAL", "CARDINAL", "CARDINAL"], ["CARDINAL", "CARDINAL", "CARDINAL", "CARDINAL", "CARDINAL", "CARDINAL", "CARDINAL", "CARDINAL", "CARDINAL", "CARDINAL", "CARDINAL", "CARDINAL", "CARDINAL", "CARDINAL", "CARDINAL", "CARDINAL", "CARDINAL", "CARDINAL", "CARDINAL", "CARDINAL", "CARDINAL", "CARDINAL", "CARDINAL", "CARDINAL", "CARDINAL", "CARDINAL", "CARDINAL", "CARDINAL", "CARDINAL", "CARDINAL", "CARDINAL"], ["CARDINAL", "CARDINAL", "CARDINAL", "CARDINAL", "CARDINAL", "CARDINAL", "CARDINAL", "CARDINAL", "CARDINAL", "CARDINAL", "CARDINAL", "CARDINAL", "CARDINAL", "CARDINAL", "CARDINAL", "CARDINAL", "CARDINAL", "CARDINAL", "CARDINAL", "CARDINAL", "CARDINAL", "CARDINAL", "CARDINAL", "CARDINAL", "CARDINAL", "CARDINAL", "CARDINAL", "CARDINAL", "CARDINAL"], ["CARDINAL", "CARDINAL", "CARDINAL", "CARDINAL", "CARDINAL", "CARDINAL", "CARDINAL", "CARDINAL", "CARDINAL", "CARDINAL", "CARDINAL", "CARDINAL", "CARDINAL", "CARDINAL", "CARDINAL", "CARDINAL", "CARDINAL", "CARDINAL", "CARDINAL", "CARDINAL", "CARDINAL", "CARDINAL", "CARDINAL", "CARDINAL", "CARDINAL", "CARDINAL", "CARDINAL", "CARDINAL", "CARDINAL"], ["CARDINAL", "CARDINAL", "CARDINAL", "CARDINAL", "CARDINAL", "CARDINAL", "CARDINAL", "CARDINAL", "CARDINAL", "CARDINAL", "CARDINAL", "CARDINAL", "CARDINAL", "CARDINAL", "CARDINAL", "CARDINAL", "CARDINAL", "CARDINAL", "CARDINAL", "CARDINAL", "CARDINAL", "CARDINAL", "CARDINAL", "CARDINAL", "CARDINAL", "CARDINAL", "CARDINAL"], [], []], "most_common": ["EMPTY", "CARDINAL", "CARDINAL", "CARDINAL", "CARDINAL", "CARDINAL", "CARDINAL", "CARDINAL", "CARDINAL", "EMPTY", "EMPTY"], "related_table": ["07tbl54.xls_TABLE42k.csv", "07shrtbl5.xls_Sheet1.csv", "Table_54_Arrests_Metropolitan_Counties_by_Sex_2017.xls_17tbl54.csv", "Table_66_Arrests_Suburban_Areas_by_Sex_2017.xls_17tbl66.csv", "07tbl48.xls_TABLE42k.csv", "Table_48_Arrests_Cities_by_Sex_2017.xls_17tbl48.csv"], "subtable": ["07tbl43b.xls_TABLE67k.csv", "07tbl68.xls_TABLE68.csv", "07tbl55b.xls_TABLE67k.csv", "07tbl47.xls_TABLE41k.csv", "Table_56_Arrest_Trends_Nonmetropolitan_Counties_2017.xls_17tbl56.csv", "07tbl73.xls_Sheet1.csv", "07tbl67c.xls_TABLE67k.csv", "Expanded_Homicide_Data_Table_15_Justifiable_Homicide_by_Weapon_Private_Citizen_2013-2017.xls_17shrtbl5.csv", "07tbl56.xls_Sheet1.csv", "Table_44_Arrest_Trends_Cities_2016-2017.xls_17tbl44.csv", "07tbl65.xls_TABLE41k.csv", "07tbl50.xls_Sheet1.csv", "Table_50_Arrest_Trends_Metropolitan_Counties_2017.xls_17tbl50.csv", "Expanded_Homicide_Data_Table_14_Justifiable_Homicide_by_Weapon_Law_Enforcement_2013-2017.xls_17shrtbl4.csv", "07tbl20.xls_Sheet1.csv", "07shrtbl14.xls_Sheet1.csv", "07tbl55c.xls_TABLE67k.csv", "07shrtbl2.xls_Sheet1.csv", "Table_65_Arrests_Suburban_Areas_Persons_Under_15_18_21_and_25_Years_of_Age_2017.xls_17tbl65.csv", "Table_47_Arrests_Cities_Persons_Under_15_18_21_and_25_Years_of_Age_2017.xls_17tbl47.csv", "07tbl44.xls_Sheet1.csv", "07shrtbl13.xls_Sheet1.csv", "07tbl49a.xls_TABLE67k.csv", "07tbl61c.xls_TABLE67k.csv", "07tbl72.xls_Sheet1.csv", "10s0594.xls_Data.csv", "10s1049.xls_Data.csv", "10s1073.xls_Data.csv", "10s1302.xls_Data.csv", "C10058_C10058.csv", "Table_20_Murder_by_State_Types_of_Weapons_2017.xls_17tbl20.csv", "07larthtbl.xls_Sheet1.csv", "07tbl03.xls_Sheet1.csv", "07tbl10ms.xls_Sheet1.csv", "Larceny-theft_Table-Larceny-theft_Percent_Distribution_within_Region_2017.xls_17larthtbl.csv", "07tbl10nv.xls_Sheet1.csv", "Table_10_Offenses_Known_to_Law_Enforcement_Virginia_by_Metropolitan_and_Nonmetropolitan_Counties_2017.xls_17tbl10va.csv", "07shrtbl7.xls_Sheet1.csv", "07robtbl1.xls_Sheet1.csv", "07tbl55a.xls_TABLE67k.csv", "07tbl30.xls_TABLE30k.csv", "Table_33_Ten_Year_Arrest_Trends_by_Sex_2017.xls_17tbl33.csv", "07tbl10nd.xls_Sheet1.csv", "07tbl61a.xls_TABLE67k.csv", "07tbl26.xls_Table 26.csv", "07tbl10co.xls_Sheet1.csv", "Robbery_Table_2_Robbery_Location_Percent_Distribution_within_Population_Group_2017.xls_17robtb2.csv", "Expanded_Homicide_Data_Table_8_Murder_Victims_by_Weapon_2013-2017.xls_17shrtbl08.csv", "07tbl34.xls_Sheet1.csv", "07robtbl2.xls_Sheet1.csv", "Robbery_Table_1_Robbery_Location_Percent_Distribution_within_Region_2017.xls_17robtbl1.csv", "07tbl67a.xls_TABLE67k.csv", "07tbl10id.xls_Sheet1.csv", "Table_32_Ten_Year_Arrest_Trends_Totals_2017.xls_17tbl32.csv", "07tbl10mt.xls_Sheet1.csv", "Table_3_Crime_in_the_United_States_Offense_and_Population_Distribution_by_Region_2017.xls_17tbl03.csv", "07tbl10ne.xls_Sheet1.csv", "07tbl10mo.xls_Sheet1.csv", "07tbl10ar.xls_Sheet1.csv", "Table_11_Offenses_Known_to_Law_Enforcement_Connecticut_by_State_Tribal_and_Other_Agencies_2017.xls_17tbl11ct.csv", "Expanded_Homicide_Data_Table_12_Murder_Circumstances_2013-2017.xls_17shrtbl12.csv", "Table_10_Offenses_Known_to_Law_Enforcement_Tennessee_by_Metropolitan_and_Nonmetropolitan_Counties_2017.xls_17tbl10tn.csv", "07shrtbl11.xls_Sheet1.csv", "07tbl21.xls_Sheet1.csv", "07tbl08al.xls_Sheet1.csv", "Table_73_Full_time_Law_Enforcement_Officers_Range_in_Rate_per_1000_Inhabitants_by_Population_Group_2017.xls_17tbl73.csv", "Table_21_Robbery_by_State_Types_of_Weapons_2017.xls_17tbl21.csv", "Table_11_Offenses_Known_to_Law_Enforcement_Nebraska_by_State_Tribal_and_Other_Agencies_2017.xls_17tbl11ne.csv", "Table_26_Percent_of_Offenses_Cleared_by_Arrest_or_Exceptional_Means_by_Geographic_Region_and_Division_2017.xls_17tbl26.csv", "Arson_Table_2_Arson_by_Type_of_Property_2017.xls_17arsontbl2.csv", "07tbl09ut.xls_Sheet1.csv", "1ead6cd7-6e15-46eb-8779-16bc26a331cc.xls_Monthly Data.csv", "frank_ermis__11033__Expansion Offer Sheet.xlsx_Example.csv", "Report 1838 & Background DataV1.xlsx_Table 1.7 2012.csv", "legal-aid-statistics-2013-14-tables.xlsx_Table 10.csv", "chapter-3-suspects.xls_S3.05.csv", "mbjvdj4nzx-2.zip_2018_Co_establishment_wormcounts.txt.csv", "10s0937.xls_Data.csv", "10s1325.xls_Data.csv", "10s1139.xls_Data.csv", "10s0300.xls_Data.csv", "10s1111.xls_Data.csv", "10s0491.xls_Data.csv", "10s0728.xls_Data.csv", "10s1090.xls_Data.csv", "10s0717.xls_Data.csv", "10s0862.xls_Data.csv", "10s1074.xls_Data.csv", "10s0894.xls_Data.csv", "10s0801.xls_Data.csv", "10s0988.xls_Data.csv", "10s1127.xls_Data.csv", "10s0594.xls_2001.csv", "10s1072.xls_Data.csv", "C10079_C10079.csv", "C10094_C10094.csv", "C10031_C10031.csv", "C10181_C10181.csv", "C10005_C10005.csv", "C10066_C10066.csv", "07shrtbl3.xls_Sheet1.csv", "07tbl41.xls_TABLE41k.csv", "07tbl53.xls_TABLE41k.csv", "07tbl66.xls_TABLE42k.csv", "07tbl62.xls_Sheet1.csv", "07tbl59.xls_TABLE41k.csv", "Table_59_Arrests_Nonmetro_Counties_Persons_Under_15_18_21_and_25_Years_of_Age_2017.xls_17tbl59.csv", "Table_60_Arrests_Nonmetropolitan_Counties_by_Sex_2017.xls_17tbl60.csv", "Table_53_Arrests_Metro_Counties_Persons_Under_15_18_21_and_25_Years_of_Age_2017.xls_17tbl53.csv", "Table_41_Arrests_Persons_Under_15_18_21_and_25_Years_of_Age_2017.xls_17tbl41.csv", "07tbl60.xls_TABLE42k.csv"], "subtable-type": ["XAAAAAAAAAAXX", "AXAAAAAAXX", "XAAAAAAAAAAXX", "XAAAAAAAAA", "XAAAAAAAAAXXX", "AXAAAAAAAXX", "XXAAAAAAAAAXX", "FAAAAAAAAAXX", "XAAAAAAAAAXXX", "XAAAAAAAXAXXX", "XAAAAAAAAA", "XAAAAAAAXAXXX", "XAAAAAAAAAXXX", "FAAAAAAAAAXX", "IAAAAAAAAAX", "FAAAAAAAAAXX", "XAAAAAAAAAAXX", "AAAAAAAAAX", "XAAAAAAAAA", "XAAAAAAAAA", "XAAAAAAXXAXX", "FAAAAAAAAAXX", "XXAAAAAAAAAXX", "XAAAAAAAAAAXX", "AXAAAAAAAXX", "CAAAAAAAAAX", "XAAAAAAAAA", "XAAAAAAAAAA", "BXAAAAAAAXX", "BAAAAAAAAX", "IAAAAAAAAA", "LAAAAAAAAAA", "LAAAAAAAAAA", "XSAAAAAAAAAA", "LAAAAAAAAAA", "XPAAAAAAAAAA", "XIAAAAAAAAAA", "XAAAAAXXXX", "LAAAAAAAA", "XAAAAAAAAAAXXX", "XXAAAAAAAAA", "XAAXAAAAAAAAXX", "XSAAAAAAAAAA", "XAAAAAAAAAAXXX", "LXAAAAAAAAAAXX", "XIAAAAAAAAAA", "XAAAAAAA", "XAAAAAXXX", "XXAAAAAAXAXXX", "XAAAAAAA", "LAAAAAAAA", "XAAAAAAAAAAXXX", "XIAAAAAAAAAA", "XAAAAAXAXAXXX", "XLAAAAAAAAAA", "LAAAAAAAAAA", "XSAAAAAAAAAA", "XSAAAAAAAAAA", "XSAAAAAAAAAA", "XPAAAAAAAAAA", "XAAAAAXXXX", "XSAAAAAAAAAA", "XAAAAAXXX", "IAAAAAAXX", "IAAAAAAAAAAX", "AXAAAAAAAXXXX", "IAAAAAAXX", "XPAAAAAAAAAA", "LXAAAAAAAAAAXX", "XAAAXAAAX", "PXAAAAAAAAAAXX", "AAAAAAAAA", "WAAXAAAAAXXX", "AAAAAAAA", "XXAAAAAAA", "NAAAAAAAAAA", "AAXAAAAAX", "BAAAAAAAAA", "FXAAAAAAAAAA", "WXAAAAAAAAAA", "WAAAAAAAA", "FAAAAAAAA", "BAAAAAAAAA", "BAAAAAAAAA", "AAAAAAAA", "WAAAAAAAAA", "BXAAAAAAAX", "IAAAAAAAAA", "XAAAAAAAAAAA", "IIAAAAAAAXA", "BAAAAAAAAA", "XAAAAAAMAAAA", "CAAAAAAAAA", "IAAAAAAAAAAX", "BAAAAAAAA", "IAAAAAAAAA", "OAAAAAAAAAA", "BAAAAAAAAAA", "AAAAAAAX", "WAAAAAAAAAA", "AAAAAAAAAXX", "XXAAAAAAAAXX", "XAAAAAAAAAXX", "XAAAAAAAAXXX", "XAAAAAAAXAXX", "XAAAAAAAAAXX", "XAAAAAAAAAXX", "XAAAAAAAAXXX", "XAAAAAAAAAXX", "XAAAAAAAAAXX", "XAAAAAAAAXXX"], "table-type": "XAAAAAAAAXX"}